Capitalism-0.2.50.dist-info/DESCRIPTION.rst
Capitalism-0.2.50.dist-info/METADATA
Capitalism-0.2.50.dist-info/RECORD
Capitalism-0.2.50.dist-info/WHEEL
Capitalism-0.2.50.dist-info/metadata.json
Capitalism-0.2.50.dist-info/top_level.txt
capitalism/__init__.py
capitalism/chain.py
capitalism/factory.py
capitalism/util.py
capitalism/worker.py
